README.md
pyproject.toml
setup.cfg
setup.py
spacestudio_satellite_client/__init__.py
spacestudio_satellite_client/api_client.py
spacestudio_satellite_client/api_response.py
spacestudio_satellite_client/configuration.py
spacestudio_satellite_client/exceptions.py
spacestudio_satellite_client/py.typed
spacestudio_satellite_client/rest.py
spacestudio_satellite_client.egg-info/PKG-INFO
spacestudio_satellite_client.egg-info/SOURCES.txt
spacestudio_satellite_client.egg-info/dependency_links.txt
spacestudio_satellite_client.egg-info/requires.txt
spacestudio_satellite_client.egg-info/top_level.txt
spacestudio_satellite_client/api/__init__.py
spacestudio_satellite_client/api/announcement_api.py
spacestudio_satellite_client/api/computations_api.py
spacestudio_satellite_client/api/notification_api.py
spacestudio_satellite_client/api/orbits_api.py
spacestudio_satellite_client/api/platforms_api.py
spacestudio_satellite_client/api/propulsion_systems_api.py
spacestudio_satellite_client/api/scenarios_api.py
spacestudio_satellite_client/api/spacecraft_geometries_api.py
spacestudio_satellite_client/api/studies_api.py
spacestudio_satellite_client/api/support_api.py
spacestudio_satellite_client/models/__init__.py
spacestudio_satellite_client/models/advanced_orbit_parameters.py
spacestudio_satellite_client/models/analytical_study_parameters.py
spacestudio_satellite_client/models/announcement.py
spacestudio_satellite_client/models/atmospheric_model.py
spacestudio_satellite_client/models/baseline_configuration.py
spacestudio_satellite_client/models/circular_altitude_orbit_parameters.py
spacestudio_satellite_client/models/circular_ground_track_repeated_orbit_parameters.py
spacestudio_satellite_client/models/comparison_item.py
spacestudio_satellite_client/models/computation.py
spacestudio_satellite_client/models/computation_mode.py
spacestudio_satellite_client/models/computation_outputs.py
spacestudio_satellite_client/models/computation_status.py
spacestudio_satellite_client/models/computation_type.py
spacestudio_satellite_client/models/context_outputs.py
spacestudio_satellite_client/models/deorbitation.py
spacestudio_satellite_client/models/display_configuration.py
